niftystocks/__init__.py
niftystocks/ns.py
niftystocks-0.1.1.dist-info/LICENSE
niftystocks-0.1.1.dist-info/METADATA
niftystocks-0.1.1.dist-info/WHEEL
niftystocks-0.1.1.dist-info/top_level.txt
niftystocks-0.1.1.dist-info/RECORD
