Metadata-Version: 2.1
Name: niftystocks
Version: 0.1.1
Summary: A small package that helps you in fetching list of specific set of stocks as a list.
Home-page: UNKNOWN
Author: Dr. Kumar B V
Author-email: kumar.bv@gmail.com
License: UNKNOWN
Platform: UNKNOWN
Classifier: Programming Language :: Python :: 3
Classifier: License :: OSI Approved :: MIT License
Classifier: Operating System :: OS Independent
Requires-Python: >=3.6
License-File: LICENSE
